keras_augm_layer/__init__.py
keras_augm_layer-1.0.6.dist-info/METADATA
keras_augm_layer-1.0.6.dist-info/WHEEL
keras_augm_layer-1.0.6.dist-info/top_level.txt
keras_augm_layer-1.0.6.dist-info/RECORD
