Metadata-Version: 2.1
Name: keras-augm-layer
Version: 1.0.6
Summary: Keras implementation of layer which performs augmentations of images using GPU.
Home-page: https://github.com/ZFTurbo/Keras-augmentation-layer
Author: Roman Sol (ZFTurbo)
Author-email: UNKNOWN
License: UNKNOWN
Platform: UNKNOWN
Requires-Dist: numpy
Requires-Dist: tensorflow (>=2.5.0)
Requires-Dist: tensorflow-addons (>=0.14.0)
